stockdata77/__init__.py
stockdata77/securities.py
stockdata77-1.0.0.dist-info/METADATA
stockdata77-1.0.0.dist-info/WHEEL
stockdata77-1.0.0.dist-info/licenses/LICENSE
stockdata77-1.0.0.dist-info/RECORD
