Metadata-Version: 2.4
Name: stockdata77
Version: 1.0.0
Summary: Interface to providers of securities trading data
Project-URL: Homepage, https://github.com/dandelion-systems/stockdata77
Project-URL: Bug Tracker, https://github.com/dandelion-systems/stockdata77/issues
Author-email: Dandelion Systems <dandelion.systems@gmail.com>
License: MIT License
License-File: LICENSE
Keywords: AV,Alpha Vantage,FMP,MOEX,NYSE,Nasdaq,stocks,trading
Classifier: License :: OSI Approved :: MIT License
Classifier: Operating System :: OS Independent
Classifier: Programming Language :: Python :: 3
Requires-Python: >=3.9
